catbhkrcfxksxnek/__init__.py
catbhkrcfxksxnek-0.0.3.dist-info/METADATA
catbhkrcfxksxnek-0.0.3.dist-info/WHEEL
catbhkrcfxksxnek-0.0.3.dist-info/top_level.txt
catbhkrcfxksxnek-0.0.3.dist-info/RECORD
